<archimate:ArchimateDiagramModel
    xmlns:xsi="http://www.w3.org/2001/XMLSchema-instance"
    xmlns:archimate="http://www.archimatetool.com/archimate"
    name="SAP Viabilidad 151129"
    id="id-44198092c7344f05845ab9cc867c0225">
  <children
      xsi:type="archimate:DiagramModelGroup"
      id="id-9ed7ae63223546aca74da870f495a1a2"
      name="Usuarios"
      textAlignment="1">
    <bounds
        x="72"
        y="47"
        width="145"
        height="349"/>
    <children
        xsi:type="archimate:DiagramModelArchimateObject"
        id="id-594e0210b3b44b88ba051909580b43c8">
      <sourceConnections
          xsi:type="archimate:DiagramModelArchimateConnection"
          id="id-70816da8153646aa91b07edab8f2ef36"
          source="id-594e0210b3b44b88ba051909580b43c8"
          target="id-8b71f14772e847f7a179fbf5aef6aa18">
        <archimateRelationship
            xsi:type="archimate:FlowRelationship"
            href="FlowRelationship_id-8cb896e12fe84f0cb5108153a3ba8417.xml#id-8cb896e12fe84f0cb5108153a3ba8417"/>
      </sourceConnections>
      <bounds
          x="12"
          y="36"
          width="120"
          height="55"/>
      <archimateElement
          xsi:type="archimate:BusinessActor"
          href="BusinessActor_id-bedd3aaf6c1c47ecabd8eca559d347d6.xml#id-bedd3aaf6c1c47ecabd8eca559d347d6"/>
    </children>
  </children>
  <children
      xsi:type="archimate:DiagramModelGroup"
      id="id-e4ba780970ce46eda9201bb77ed00b0c"
      name="Frontend"
      textAlignment="1">
    <bounds
        x="240"
        y="46"
        width="169"
        height="351"/>
    <children
        xsi:type="archimate:DiagramModelArchimateObject"
        id="id-8b71f14772e847f7a179fbf5aef6aa18"
        targetConnections="id-70816da8153646aa91b07edab8f2ef36">
      <sourceConnections
          xsi:type="archimate:DiagramModelArchimateConnection"
          id="id-04edf295efdb48658f8049ff2cefb172"
          source="id-8b71f14772e847f7a179fbf5aef6aa18"
          target="id-469919427ab44aa5a488431ba925379c">
        <archimateRelationship
            xsi:type="archimate:FlowRelationship"
            href="FlowRelationship_id-87b2f10904ae4fb6bbd9360bf9a701eb.xml#id-87b2f10904ae4fb6bbd9360bf9a701eb"/>
      </sourceConnections>
      <bounds
          x="12"
          y="36"
          width="145"
          height="301"/>
      <archimateElement
          xsi:type="archimate:ApplicationComponent"
          href="ApplicationComponent_59871134.xml#59871134"/>
    </children>
  </children>
  <children
      xsi:type="archimate:DiagramModelGroup"
      id="id-49254b4e822f4b0684f49f332a788bb2"
      name="Backend"
      textAlignment="1">
    <bounds
        x="432"
        y="40"
        width="433"
        height="357"/>
    <children
        xsi:type="archimate:DiagramModelArchimateObject"
        id="id-469919427ab44aa5a488431ba925379c"
        targetConnections="id-04edf295efdb48658f8049ff2cefb172">
      <bounds
          x="12"
          y="36"
          width="409"
          height="301"/>
      <children
          xsi:type="archimate:DiagramModelArchimateObject"
          id="id-d88e6c56a4a746068780ec6b78d2077f">
        <bounds
            x="12"
            y="36"
            width="384"
            height="36"/>
        <archimateElement
            xsi:type="archimate:ApplicationComponent"
            href="ApplicationComponent_31ada80a.xml#31ada80a"/>
      </children>
      <children
          xsi:type="archimate:DiagramModelArchimateObject"
          id="id-e0a0a683ae874b95978f2acdd3310190"
          fillColor="#ffff00">
        <bounds
            x="12"
            y="96"
            width="120"
            height="55"/>
        <archimateElement
            xsi:type="archimate:ApplicationComponent"
            href="ApplicationComponent_0f3d93ae.xml#0f3d93ae"/>
      </children>
      <children
          xsi:type="archimate:DiagramModelArchimateObject"
          id="id-1b1a8a90929c48568c6e66a97b47ac8f">
        <bounds
            x="144"
            y="96"
            width="120"
            height="55"/>
        <archimateElement
            xsi:type="archimate:ApplicationComponent"
            href="ApplicationComponent_76ad0d1d.xml#76ad0d1d"/>
      </children>
      <children
          xsi:type="archimate:DiagramModelArchimateObject"
          id="id-384ba3e79f804df1941ca2d71b74f907"
          fillColor="#ffff00">
        <bounds
            x="276"
            y="96"
            width="120"
            height="55"/>
        <archimateElement
            xsi:type="archimate:ApplicationComponent"
            href="ApplicationComponent_ef950d70.xml#ef950d70"/>
      </children>
      <children
          xsi:type="archimate:DiagramModelArchimateObject"
          id="id-b070712250174bc68b784df7121b113b">
        <bounds
            x="276"
            y="216"
            width="120"
            height="55"/>
        <archimateElement
            xsi:type="archimate:ApplicationComponent"
            href="ApplicationComponent_e26a6789.xml#e26a6789"/>
      </children>
      <children
          xsi:type="archimate:DiagramModelArchimateObject"
          id="id-0c8bcf10f7c640d098af7b249d3da371">
        <bounds
            x="12"
            y="156"
            width="120"
            height="55"/>
        <archimateElement
            xsi:type="archimate:ApplicationComponent"
            href="ApplicationComponent_5b11a748.xml#5b11a748"/>
      </children>
      <children
          xsi:type="archimate:DiagramModelArchimateObject"
          id="id-b8307a9453d241c9abce2b65f48caf0a">
        <bounds
            x="144"
            y="156"
            width="120"
            height="55"/>
        <archimateElement
            xsi:type="archimate:ApplicationComponent"
            href="ApplicationComponent_8bf98d31.xml#8bf98d31"/>
      </children>
      <children
          xsi:type="archimate:DiagramModelArchimateObject"
          id="id-74282c18653a432ba3097d244ee3c729">
        <bounds
            x="12"
            y="216"
            width="120"
            height="55"/>
        <archimateElement
            xsi:type="archimate:ApplicationComponent"
            href="ApplicationComponent_1ec35f62.xml#1ec35f62"/>
      </children>
      <children
          xsi:type="archimate:DiagramModelArchimateObject"
          id="id-6ed47998e2e645f68328e3341b633de8">
        <bounds
            x="144"
            y="216"
            width="120"
            height="55"/>
        <archimateElement
            xsi:type="archimate:ApplicationComponent"
            href="ApplicationComponent_15792496.xml#15792496"/>
      </children>
      <archimateElement
          xsi:type="archimate:ApplicationComponent"
          href="ApplicationComponent_fb0dde3b.xml#fb0dde3b"/>
    </children>
  </children>
</archimate:ArchimateDiagramModel>
